{"cameraMode":{"drawMode":0,"name":"Shaded","section":"Shading Mode"},"sceneLighting":false,"audioPlay":false,"sceneViewState":{"m_AlwaysRefresh":false,"showFog":true,"showSkybox":true,"showFlares":true,"showImageEffects":true,"showParticleSystems":true,"showVisualEffectGraphs":true,"m_FxEnabled":true},"in2DMode":false,"pivot":{"x":-6.220980644226074,"y":4.43906307220459,"z":-11.648529052734375},"rotation":{"x":0.009135780856013298,"y":-0.984138011932373,"z":0.05319536104798317,"w":0.1690284013748169},"size":1.904052734375,"orthographic":false}